augmentation/__init__.py
augmentation/augmentation_2d.py
augmentation/augmentation_3d.py
augmentation/img/__init__.py
augmentation-0.7.dist-info/LICENSE
augmentation-0.7.dist-info/METADATA
augmentation-0.7.dist-info/WHEEL
augmentation-0.7.dist-info/top_level.txt
augmentation-0.7.dist-info/RECORD
