Metadata-Version: 2.1
Name: augmentation
Version: 0.7
Summary: A library, based on PyTorch, that performs data augmentation on the GPU
Home-page: https://github.com/JorisRoels/augmentation
Author: Joris Roels
Author-email: jorisb.roels@ugent.be
License: UNKNOWN
Platform: UNKNOWN
Classifier: Programming Language :: Python :: 3
Classifier: License :: OSI Approved :: MIT License
Classifier: Operating System :: OS Independent
Requires-Python: >=3.6
